dash_xinet/__init__.py
dash_xinet/server.py
dash_xinet/design/__init__.py
dash_xinet/design/template.py
dash_xinet/utils/__init__.py
dash_xinet/utils/nav.py
dash_xinet-0.2.5.dist-info/LICENSE
dash_xinet-0.2.5.dist-info/METADATA
dash_xinet-0.2.5.dist-info/WHEEL
dash_xinet-0.2.5.dist-info/top_level.txt
dash_xinet-0.2.5.dist-info/RECORD
