Metadata-Version: 2.1
Name: dash-xinet
Version: 0.2.5
Summary: Dash App
Home-page: https://github.com/xinetzone/dash-xinet
Author: xinetzone
Author-email: xinzone@outlook.com
Classifier: Programming Language :: Python :: 3
Classifier: Development Status :: 2 - Pre-Alpha
Classifier: Operating System :: Microsoft :: Windows :: Windows 10
Classifier: Operating System :: POSIX :: Linux
Requires-Python: >=3.8
License-File: LICENSE
